MANIFEST.in
requirements.txt
setup.cfg
setup.py
Mocha.egg-info/PKG-INFO
Mocha.egg-info/SOURCES.txt
Mocha.egg-info/dependency_links.txt
Mocha.egg-info/entry_points.txt
Mocha.egg-info/not-zip-safe
Mocha.egg-info/requires.txt
Mocha.egg-info/top_level.txt
mocha/.DS_Store
mocha/__about__.py
mocha/__about__.pyc
mocha/__init__.py
mocha/__init__.pyc
mocha/cli.py
mocha/cli.pyc
mocha/core.py
mocha/core.pyc
mocha/decorators.py
mocha/decorators.pyc
mocha/exceptions.py
mocha/exceptions.pyc
mocha/ext.py
mocha/ext.pyc
mocha/render.py
mocha/render.pyc
mocha/signals.py
mocha/signals.pyc
mocha/utils.py
mocha/utils.pyc
mocha/__pycache__/__about__.cpython-35.pyc
mocha/__pycache__/__about__.cpython-36.pyc
mocha/__pycache__/__init__.cpython-35.pyc
mocha/__pycache__/__init__.cpython-36.pyc
mocha/__pycache__/cli.cpython-35.pyc
mocha/__pycache__/cli.cpython-36.pyc
mocha/__pycache__/core.cpython-35.pyc
mocha/__pycache__/core.cpython-36.pyc
mocha/__pycache__/decorators.cpython-35.pyc
mocha/__pycache__/decorators.cpython-36.pyc
mocha/__pycache__/exceptions.cpython-35.pyc
mocha/__pycache__/exceptions.cpython-36.pyc
mocha/__pycache__/ext.cpython-35.pyc
mocha/__pycache__/ext.cpython-36.pyc
mocha/__pycache__/utils.cpython-35.pyc
mocha/__pycache__/utils.cpython-36.pyc
mocha/contrib/.DS_Store
mocha/contrib/__init__.py
mocha/contrib/__init__.pyc
mocha/contrib/app_data.py
mocha/contrib/app_data.pyc
mocha/contrib/__pycache__/__init__.cpython-35.pyc
mocha/contrib/__pycache__/__init__.cpython-36.pyc
mocha/contrib/auth/__init__.py
mocha/contrib/auth/__init__.pyc
mocha/contrib/auth/decorators.py
mocha/contrib/auth/decorators.pyc
mocha/contrib/auth/exceptions.py
mocha/contrib/auth/exceptions.pyc
mocha/contrib/auth/models.py
mocha/contrib/auth/models.pyc
mocha/contrib/auth/oauth.py
mocha/contrib/auth/oauth.pyc
mocha/contrib/auth/signals.py
mocha/contrib/auth/signals.pyc
mocha/contrib/static/.DS_Store
mocha/contrib/static/assets.yml
mocha/contrib/static/contrib/.DS_Store
mocha/contrib/static/contrib/init-form-validator.js
mocha/contrib/static/contrib/admin/css/admin.css
mocha/contrib/static/contrib/admin/css/admin.css.map
mocha/contrib/static/contrib/admin/css/admin.scss
